imd_handler/__init__.py
imd_handler/imd_bands.py
imd_handler/imd_handler.py
imd_handler/imd_lambda.py
imd_handler/test_main.py
imd_handler-0.0.422.dist-info/METADATA
imd_handler-0.0.422.dist-info/RECORD
imd_handler-0.0.422.dist-info/WHEEL
imd_handler-0.0.422.dist-info/top_level.txt
