Metadata-Version: 2.1
Name: imd-handler
Version: 0.0.422
Summary: Set of stuff for ingesting, discovery, editing and storing DG IMD files
Home-page: https://github.com/DigitalGlobe/IMDiddler
Author: G to_tha K to_tha W
Author-email: gewatson@digitalglobe.com
License: UNKNOWN
Platform: UNKNOWN
Classifier: Programming Language :: Python :: 3
Classifier: License :: OSI Approved :: MIT License
Classifier: Operating System :: OS Independent
